pesapal_sdk/__init__.py
pesapal_sdk/client.py
pesapal_sdk/constants.py
pesapal_sdk/auth/__init__.py
pesapal_sdk/auth/token_manager.py
pesapal_sdk/models/__init__.py
pesapal_sdk/models/request.py
pesapal_sdk/resources/__init__.py
pesapal_sdk/resources/base.py
pesapal_sdk/resources/ipn.py
pesapal_sdk/resources/transactions.py
pesapal_sdk-0.1.5.dist-info/licenses/LICENSE.md
pesapal_sdk-0.1.5.dist-info/METADATA
pesapal_sdk-0.1.5.dist-info/WHEEL
pesapal_sdk-0.1.5.dist-info/top_level.txt
pesapal_sdk-0.1.5.dist-info/RECORD
