Metadata-Version: 2.4
Name: pesapal_sdk
Version: 0.1.5
Summary: Python wrapper for the Pesapal API
Author-email: Kevin Kimani <kimanikevin254@gmail.com>
License-Expression: MIT
Project-URL: Homepage, https://github.com/kimanikevin254/pesapal-python-sdk
Project-URL: Repository, https://github.com/kimanikevin254/pesapal-python-sdk
Project-URL: Issues, https://github.com/kimanikevin254/pesapal-python-sdk/issues
Keywords: pesapal,sdk,payments
Classifier: Development Status :: 5 - Production/Stable
Classifier: Intended Audience :: Developers
Classifier: Programming Language :: Python :: 3
Classifier: Programming Language :: Python :: 3.8
Classifier: Programming Language :: Python :: 3.9
Classifier: Programming Language :: Python :: 3.10
Classifier: Programming Language :: Python :: 3.11
Classifier: Programming Language :: Python :: 3.12
Classifier: Topic :: Software Development :: Libraries :: Python Modules
Classifier: Typing :: Typed
Requires-Python: >=3.8
License-File: LICENSE.md
Requires-Dist: requests>=2.28.0
Provides-Extra: dev
Requires-Dist: pytest>=7.0; extra == "dev"
Requires-Dist: pytest-cov>=4.0; extra == "dev"
Requires-Dist: pytest-mock>=3.10; extra == "dev"
Dynamic: license-file
